{
  "unquoted_key": "test",
  "_unquoted": "test",
  "test-key": "test",
  "-test": "test",
  ".key": "test",
  "trailing": "test",
  "trailing2": "test",
  "# c1": "test",
  "foo # c1 bar": "test",
  "// c2": "test",
  "foo // c2 bar": "test",
  "/* c3 */": "test",
  "foo /* c3 */ bar": "test",
  "/*": "test",
  "foo /* bar": "test",
  ":": "test",
  "foo:bar": "test",
  "{": "test",
  "foo{bar": "test",
  "}": "test",
  "foo}bar": "test",
  "[": "test",
  "foo[bar": "test",
  "]": "test",
  "foo]bar": "test"
}